svc_viz/__init__.py
svc_viz/utils.py
svc_viz/viz_gwr.py
svc_viz-0.1.2.dist-info/licenses/LICENSE
tests/__init__.py
tests/test_utils.py
svc_viz-0.1.2.dist-info/METADATA
svc_viz-0.1.2.dist-info/WHEEL
svc_viz-0.1.2.dist-info/top_level.txt
svc_viz-0.1.2.dist-info/RECORD
