Metadata-Version: 2.4
Name: svc_viz
Version: 0.1.2
Summary: A python software package for visualizing the results of spatially varying coefficient (SVC) models, enhancing reproducibility and replicability
Home-page: https://github.com/marquisvictor/svc-viz
Author: Victor Irekponor, Taylor Oshan
Author-email: vireks@umd.edu
Classifier: Programming Language :: Python :: 3
Classifier: License :: OSI Approved :: GNU General Public License v2 (GPLv2)
Classifier: Operating System :: OS Independent
License-File: LICENSE
Dynamic: author
Dynamic: author-email
Dynamic: classifier
Dynamic: home-page
Dynamic: license-file
Dynamic: summary
